embcli_core/__init__.py
embcli_core/cli.py
embcli_core/document.py
embcli_core/document_loader.py
embcli_core/hookspecs.py
embcli_core/models.py
embcli_core/plugins.py
embcli_core/py.typed
embcli_core/similarities.py
embcli_core/vector_stores.py
embcli_core/synth_data/cat-names-en.csv
embcli_core/synth_data/cat-names-ja.csv
embcli_core/synth_data/dishes-en.csv
embcli_core/synth_data/dishes-ja.csv
embcli_core/synth_data/movies-en.csv
embcli_core/synth_data/movies-ja.csv
embcli_core/synth_data/tourist-spots-en.csv
embcli_core/synth_data/tourist-spots-ja.csv
embcli_core/vector_store/__init__.py
embcli_core/vector_store/lancedb.py
embcli_core-0.1.2.dist-info/METADATA
embcli_core-0.1.2.dist-info/WHEEL
embcli_core-0.1.2.dist-info/entry_points.txt
embcli_core-0.1.2.dist-info/RECORD
